README.md
setup.py
galileodb/__init__.py
galileodb/db.py
galileodb/factory.py
galileodb/model.py
galileodb/trace.py
galileodb/cli/__init__.py
galileodb/cli/recorder.py
galileodb/recorder/__init__.py
galileodb/recorder/events.py
galileodb/recorder/recorder.py
galileodb/recorder/telemetry.py
galileodb/reporter/__init__.py
galileodb/reporter/events.py
galileodb/reporter/telemetry.py
galileodb/sql/__init__.py
galileodb/sql/adapter.py
galileodb/sql/schema.sql
galileodb/sql/driver/__init__.py
galileodb/sql/driver/mysql.py
galileodb/sql/driver/sqlite.py
mc2_galileo_db.egg-info/PKG-INFO
mc2_galileo_db.egg-info/SOURCES.txt
mc2_galileo_db.egg-info/dependency_links.txt
mc2_galileo_db.egg-info/entry_points.txt
mc2_galileo_db.egg-info/requires.txt
mc2_galileo_db.egg-info/top_level.txt
tests/__init__.py
tests/test_trace.py
tests/testutils.py
tests/recorder/__init__.py
tests/recorder/test_events.py
tests/recorder/test_telemetry.py
tests/sql/__init__.py
tests/sql/adapter.py
tests/sql/driver/__init__.py
tests/sql/driver/test_sqlite.py