Metadata-Version: 2.1
Name: mc2-galileo-db
Version: 0.2.0
Summary: Galileo DB: Gateway and client tools for the Galileo Experiment DB
Home-page: https://git.dsg.tuwien.ac.at/mc2/galileo-db
Author: Thomas Rausch
Author-email: t.rausch@dsg.tuwien.ac.at
License: UNKNOWN
Platform: UNKNOWN
Classifier: Programming Language :: Python :: 3
Classifier: Operating System :: OS Independent
